fotmob/__init__.py
fotmob/fotmob.py
fotmob-0.0.2.dist-info/LICENSE
fotmob-0.0.2.dist-info/METADATA
fotmob-0.0.2.dist-info/WHEEL
fotmob-0.0.2.dist-info/top_level.txt
fotmob-0.0.2.dist-info/RECORD
