Metadata-Version: 2.1
Name: fotmob
Version: 0.0.2
Summary: A Python wrapper around the unofficial FotMob API
Home-page: UNKNOWN
Author: MatsAndT
Author-email: 
License: UNKNOWN
Keywords: python,fotmob,api,fotball,score,data
Platform: UNKNOWN
Classifier: Development Status :: 1 - Planning
Classifier: Intended Audience :: Developers
Classifier: Programming Language :: Python :: 3
Classifier: Operating System :: Unix
Classifier: Operating System :: MacOS :: MacOS X
Classifier: Operating System :: Microsoft :: Windows
